ggcorrplot/__init__.py
ggcorrplot/_ggcorrplot.py
ggcorrplot/utils.py
ggcorrplot-0.1.0.dist-info/METADATA
ggcorrplot-0.1.0.dist-info/WHEEL
ggcorrplot-0.1.0.dist-info/top_level.txt
ggcorrplot-0.1.0.dist-info/RECORD
