Metadata-Version: 2.4
Name: ggcorrplot
Version: 0.1.0
Summary: Visualization of a Correlation Matrix using plotnine
Home-page: https://github.com/enfantbenidedieu/ggcorrplot
Author: Duvérier DJIFACK ZEBAZE
Author-email: djifacklab@gmail.com
Project-URL: Bug Reports, https://github.com/enfantbenidedieu/ggcorrplot/issues
Project-URL: Source, https://github.com/enfantbenidedieu/ggcorrplot
Project-URL: Documentation, https://ggcorrplot.readthedocs.io
Keywords: correlation matrix,matrix of correlation p-values,plotnine,ggplot
Classifier: Intended Audience :: Science/Research
Classifier: Intended Audience :: Developers
Classifier: Programming Language :: Python
Classifier: Topic :: Software Development
Classifier: Topic :: Scientific/Engineering
Classifier: License :: OSI Approved :: MIT License
Classifier: Operating System :: OS Independent
Classifier: Programming Language :: Python :: 3
Classifier: Programming Language :: Python :: 3.11
Requires-Python: >=3.11
Requires-Dist: numpy>=2.3.4
Requires-Dist: pandas>=2.3.3
Requires-Dist: scipy>=1.16.3
Requires-Dist: plotnine>=0.15.1
Dynamic: author
Dynamic: author-email
Dynamic: classifier
Dynamic: description
Dynamic: description-content-type
Dynamic: home-page
Dynamic: keywords
Dynamic: project-url
Dynamic: requires-dist
Dynamic: requires-python
Dynamic: summary
